ravenclaw/DataEnclosure.py
ravenclaw/__init__.py
ravenclaw/display.py
ravenclaw/example_dataframes.py
ravenclaw/get_data_types.py
ravenclaw/get_difference.py
ravenclaw/get_numeric_columns.py
ravenclaw/num_rows.py
ravenclaw/package_info.py
ravenclaw/read_excel.py
ravenclaw/data/__init__.py
ravenclaw/data/get_sparql_dataframe.py
ravenclaw/data/wikidata/__init__.py
ravenclaw/data/wikidata/get_books.py
ravenclaw/data/wikidata/get_companies.py
ravenclaw/data/wikidata/get_countries.py
ravenclaw/data/wikidata/get_exchanges.py
ravenclaw/file/__init__.py
ravenclaw/file/read_excel.py
ravenclaw/fuzzy/__init__.py
ravenclaw/fuzzy/fuzzy_left_merge.py
ravenclaw/preprocessing/Normalizer.py
ravenclaw/preprocessing/OneHotEncoder.py
ravenclaw/preprocessing/Polynomial.py
ravenclaw/preprocessing/__init__.py
ravenclaw/sampling/UpSampler.py
ravenclaw/sampling/__init__.py
ravenclaw/sampling/balance_sample.py
ravenclaw/sampling/sample_by_id.py
ravenclaw/sampling/sample_per_group.py
ravenclaw/sampling/sampler.py
ravenclaw/sampling/split_data.py
ravenclaw/time/__init__.py
ravenclaw/time/add_time.py
ravenclaw/time/as_yearmonth.py
ravenclaw/time/construct_timeseries.py
ravenclaw/time/get_calendar.py
ravenclaw/time/replace_date_part.py
ravenclaw/time/to_date_part.py
ravenclaw/wrangling/__init__.py
ravenclaw/wrangling/as_numeric.py
ravenclaw/wrangling/as_string.py
ravenclaw/wrangling/bring_to_front.py
ravenclaw/wrangling/columns_are_unique.py
ravenclaw/wrangling/create_data_from_combinations.py
ravenclaw/wrangling/fast_merge.py
ravenclaw/wrangling/fill_na.py
ravenclaw/wrangling/fill_with_regression.py
ravenclaw/wrangling/find_duplicated_columns.py
ravenclaw/wrangling/join_and_preserve_types.py
ravenclaw/wrangling/join_wisely.py
ravenclaw/wrangling/long_to_wide.py
ravenclaw/wrangling/min_max.py
ravenclaw/wrangling/reset_column_index.py
ravenclaw/wrangling/select_columns.py
ravenclaw/wrangling/select_extreme.py
ravenclaw/wrangling/set_value_where.py
ravenclaw/wrangling/split_rows.py
ravenclaw-2020.11.12.dist-info/LICENSE
ravenclaw-2020.11.12.dist-info/METADATA
ravenclaw-2020.11.12.dist-info/WHEEL
ravenclaw-2020.11.12.dist-info/top_level.txt
ravenclaw-2020.11.12.dist-info/RECORD
