Metadata-Version: 1.0
Name: ravenclaw
Version: 2020.11.12
Summary: For data wrangling.
Home-page: https://github.com/idin/ravenclaw
Author: Idin
Author-email: py@idin.ca
License: MIT
Platform: UNKNOWN
